README.md
setup.py
casadi_hotfixes/__init__.py
casadi_hotfixes.egg-info/PKG-INFO
casadi_hotfixes.egg-info/SOURCES.txt
casadi_hotfixes.egg-info/dependency_links.txt
casadi_hotfixes.egg-info/top_level.txt
casadi_hotfixes.egg-info/zip-safe