Metadata-Version: 1.0
Name: casadi_hotfixes
Version: 1.0
Summary: Collections of patches for CasADi Python
Home-page: http://github.com/storborg/funniest
Author: Joris Gillis
Author-email: joris.gillis42@gmail.com
License: MIT
Platform: UNKNOWN
